scaffoldry/__init__.py
scaffoldry/generators/__init__.py
scaffoldry/generators/core.py
scaffoldry/generators/pygen.py
scaffoldry/init_template_objs/__init__.py
scaffoldry/init_template_objs/python_pkg.py
scaffoldry/main.py
scaffoldry/main_arguments.py
scaffoldry/models_pkg/__init__.py
scaffoldry/models_pkg/enum_values.py
scaffoldry/models_pkg/models.py
scaffoldry/templates/__init__.py
scaffoldry/templates/core.py
scaffoldry/templates/pypackage/.flake8.j2
scaffoldry/templates/pypackage/.gitignore.j2
scaffoldry/templates/pypackage/.pre-commit-config.yaml.j2
scaffoldry/templates/pypackage/__init__.py
scaffoldry/templates/pypackage/checks.sh.j2
scaffoldry/templates/pypackage/ci.yml.j2
scaffoldry/templates/pypackage/main.py.j2
scaffoldry/templates/pypackage/paths.py
scaffoldry/templates/pypackage/pyproject.toml.j2
scaffoldry/templates/pypackage/release.yml.j2
scaffoldry-0.0.1a3.dist-info/METADATA
scaffoldry-0.0.1a3.dist-info/WHEEL
scaffoldry-0.0.1a3.dist-info/entry_points.txt
scaffoldry-0.0.1a3.dist-info/RECORD
