Metadata-Version: 2.4
Name: scaffoldry
Version: 0.0.1a3
Summary: Package to generate projects
License: MIT
Author: Carlos Bustamante Garres
Author-email: c.bustamante.garres@gmail.com
Requires-Python: >=3.10
Classifier: License :: OSI Approved :: MIT License
Classifier: Programming Language :: Python :: 3
Classifier: Programming Language :: Python :: 3.10
Classifier: Programming Language :: Python :: 3.11
Classifier: Programming Language :: Python :: 3.12
Classifier: Programming Language :: Python :: 3.13
Classifier: Programming Language :: Python :: 3.14
Provides-Extra: dev
Requires-Dist: black (==25.11.0) ; extra == "dev"
Requires-Dist: isort (==7.0.0) ; extra == "dev"
Requires-Dist: jinja2 (==3.1.6)
Requires-Dist: mypy (==1.19.0) ; extra == "dev"
Requires-Dist: poetry (==2.2.1) ; extra == "dev"
Requires-Dist: pre_commit (==4.5.0)
Requires-Dist: pydantic (==2.12.5)
Requires-Dist: pytest (==9.0.2) ; extra == "dev"
Requires-Dist: pytest_cov (==7.0.0) ; extra == "dev"
Requires-Dist: typer (==0.20.0)
Requires-Dist: wemake-python-styleguide (==1.4.0) ; extra == "dev"
Project-URL: Homepage, https://github.com/cabuga/scaffoldry
